s3upload/views.py
s3upload/forms.py
s3upload/settings.py
s3upload/models.py
s3upload/__init__.py
s3upload/static/s3upload/dropzone.js
s3upload/static/s3upload/dropzone-options.js
s3upload/static/s3upload/images/spritemap.png
s3upload/static/s3upload/images/spritemap@2x.png
s3upload/static/s3upload/css/dropzone.css
s3upload/templates/base.html
s3upload/templates/s3upload/_dropzone_form.html
s3upload/templates/s3upload/base.html
s3upload/templates/s3upload/dropzone_form.html
s3upload/templates/s3upload/form.html
s3upload/templates/s3upload/_form.html
django_storages_s3upload-0.1.6.dist-info/WHEEL
django_storages_s3upload-0.1.6.dist-info/pydist.json
django_storages_s3upload-0.1.6.dist-info/DESCRIPTION.rst
django_storages_s3upload-0.1.6.dist-info/RECORD
django_storages_s3upload-0.1.6.dist-info/METADATA
django_storages_s3upload-0.1.6.dist-info/top_level.txt
