Metadata-Version: 2.0
Name: django-storages-s3upload
Version: 0.1.6
Summary: Direct (client-side) HTTP POST file upload to S3 using Django forms/views.
Home-page: https://github.com/mattaustin/django-storages-s3upload
Author: Matt Austin
Author-email: mail@mattaustin.me.uk
License: UNKNOWN
Keywords: s3,upload,post,django-storages,django
Platform: UNKNOWN
Classifier: Development Status :: 3 - Alpha
Classifier: Environment :: Web Environment
Classifier: Framework :: Django
Classifier: License :: OSI Approved :: Apache Software License
Classifier: Programming Language :: Python
Classifier: Programming Language :: Python :: 2
Classifier: Programming Language :: Python :: 2.7
Classifier: Topic :: Software Development :: Libraries :: Python Modules
Requires-Dist: boto
Requires-Dist: django
Requires-Dist: django-storages
Requires-Dist: python-magic
